odoo/addons/hr_expense_portal/README.rst
odoo/addons/hr_expense_portal/__init__.py
odoo/addons/hr_expense_portal/__manifest__.py
odoo/addons/hr_expense_portal/controllers/__init__.py
odoo/addons/hr_expense_portal/controllers/expense_portal.py
odoo/addons/hr_expense_portal/i18n/hr_expense_portal.pot
odoo/addons/hr_expense_portal/i18n/it.po
odoo/addons/hr_expense_portal/readme/CONTRIBUTORS.rst
odoo/addons/hr_expense_portal/readme/CREDITS.rst
odoo/addons/hr_expense_portal/readme/DESCRIPTION.rst
odoo/addons/hr_expense_portal/security/ir.model.access.csv
odoo/addons/hr_expense_portal/security/security.xml
odoo/addons/hr_expense_portal/static/description/icon.png
odoo/addons/hr_expense_portal/static/description/index.html
odoo/addons/hr_expense_portal/tests/__init__.py
odoo/addons/hr_expense_portal/tests/test_hr_expense_portal.py
odoo/addons/hr_expense_portal/views/expense_template.xml
odoo13_addon_hr_expense_portal-13.0.1.0.2.dev6.dist-info/METADATA
odoo13_addon_hr_expense_portal-13.0.1.0.2.dev6.dist-info/WHEEL
odoo13_addon_hr_expense_portal-13.0.1.0.2.dev6.dist-info/top_level.txt
odoo13_addon_hr_expense_portal-13.0.1.0.2.dev6.dist-info/RECORD
